<Experiment59>
    <start_pos>
        <x>-18.183</x>
        <y>18.1806</y>
        <vx>0</vx>
        <vy>0</vy>
    </start_pos>
    <goal_pos>
        <x>-15.2091</x>
        <y>13.085</y>
        <vx>0</vx>
        <vy>0</vy>
    </goal_pos>
    <eta>0.0001</eta>
    <sig_obs>29000</sig_obs>
    <sig0>0.18272</sig0>
    <sigT>0.10216</sigT>
    <saving_prefix>/home/hzyu/git/VIMP/vimp/save/BRM_80nodes_v1/exp59</saving_prefix>
</Experiment59>
<Experiment70>
    <start_pos>
        <x>5.7862</x>
        <y>17.471</y>
        <vx>0</vx>
        <vy>0</vy>
    </start_pos>
    <goal_pos>
        <x>9.4765</x>
        <y>14.0824</y>
        <vx>0</vx>
        <vy>0</vy>
    </goal_pos>
    <eta>0.0001</eta>
    <sig_obs>29000</sig_obs>
    <sig0>0.17246</sig0>
    <sigT>0.053688</sigT>
    <saving_prefix>/home/hzyu/git/VIMP/vimp/save/BRM_80nodes_v1/exp70</saving_prefix>
</Experiment70>
<Experiment69>
    <start_pos>
        <x>-1.6186</x>
        <y>14.9834</y>
        <vx>0</vx>
        <vy>0</vy>
    </start_pos>
    <goal_pos>
        <x>0.27386</x>
        <y>9.4536</y>
        <vx>0</vx>
        <vy>0</vy>
    </goal_pos>
    <eta>0.0001</eta>
    <sig_obs>29000</sig_obs>
    <sig0>0.6796</sig0>
    <sigT>0.10507</sigT>
    <saving_prefix>/home/hzyu/git/VIMP/vimp/save/BRM_80nodes_v1/exp69</saving_prefix>
</Experiment69>
<Experiment68>
    <start_pos>
        <x>-1.6186</x>
        <y>14.9834</y>
        <vx>0</vx>
        <vy>0</vy>
    </start_pos>
    <goal_pos>
        <x>-6.6271</x>
        <y>18.27</y>
        <vx>0</vx>
        <vy>0</vy>
    </goal_pos>
    <eta>0.0001</eta>
    <sig_obs>29000</sig_obs>
    <sig0>0.6796</sig0>
    <sigT>0.16359</sigT>
    <saving_prefix>/home/hzyu/git/VIMP/vimp/save/BRM_80nodes_v1/exp68</saving_prefix>
</Experiment68>
<Experiment67>
    <start_pos>
        <x>-1.6186</x>
        <y>14.9834</y>
        <vx>0</vx>
        <vy>0</vy>
    </start_pos>
    <goal_pos>
        <x>-5.0071</x>
        <y>10.1534</y>
        <vx>0</vx>
        <vy>0</vy>
    </goal_pos>
    <eta>0.0001</eta>
    <sig_obs>29000</sig_obs>
    <sig0>0.6796</sig0>
    <sigT>0.06159</sigT>
    <saving_prefix>/home/hzyu/git/VIMP/vimp/save/BRM_80nodes_v1/exp67</saving_prefix>
</Experiment67>
<Experiment66>
    <start_pos>
        <x>-15.0401</x>
        <y>-7.3388</y>
        <vx>0</vx>
        <vy>0</vy>
    </start_pos>
    <goal_pos>
        <x>-9</x>
        <y>-7</y>
        <vx>0</vx>
        <vy>0</vy>
    </goal_pos>
    <eta>0.0001</eta>
    <sig_obs>29000</sig_obs>
    <sig0>0.31967</sig0>
    <sigT>0.22641</sigT>
    <saving_prefix>/home/hzyu/git/VIMP/vimp/save/BRM_80nodes_v1/exp66</saving_prefix>
</Experiment66>
<Experiment65>
    <start_pos>
        <x>-15.0401</x>
        <y>-7.3388</y>
        <vx>0</vx>
        <vy>0</vy>
    </start_pos>
    <goal_pos>
        <x>-17.84</x>
        <y>-2.836</y>
        <vx>0</vx>
        <vy>0</vy>
    </goal_pos>
    <eta>0.0001</eta>
    <sig_obs>29000</sig_obs>
    <sig0>0.31967</sig0>
    <sigT>0.26844</sigT>
    <saving_prefix>/home/hzyu/git/VIMP/vimp/save/BRM_80nodes_v1/exp65</saving_prefix>
</Experiment65>
<Experiment64>
    <start_pos>
        <x>-15.0401</x>
        <y>-7.3388</y>
        <vx>0</vx>
        <vy>0</vy>
    </start_pos>
    <goal_pos>
        <x>-9.1456</x>
        <y>-7.0836</y>
        <vx>0</vx>
        <vy>0</vy>
    </goal_pos>
    <eta>0.0001</eta>
    <sig_obs>29000</sig_obs>
    <sig0>0.31967</sig0>
    <sigT>0.24794</sigT>
    <saving_prefix>/home/hzyu/git/VIMP/vimp/save/BRM_80nodes_v1/exp64</saving_prefix>
</Experiment64>
<Experiment63>
    <start_pos>
        <x>-11.7044</x>
        <y>17.8892</y>
        <vx>0</vx>
        <vy>0</vy>
    </start_pos>
    <goal_pos>
        <x>-6.6271</x>
        <y>18.27</y>
        <vx>0</vx>
        <vy>0</vy>
    </goal_pos>
    <eta>0.0001</eta>
    <sig_obs>29000</sig_obs>
    <sig0>0.25515</sig0>
    <sigT>0.16359</sigT>
    <saving_prefix>/home/hzyu/git/VIMP/vimp/save/BRM_80nodes_v1/exp63</saving_prefix>
</Experiment63>
<Experiment62>
    <start_pos>
        <x>-11.7044</x>
        <y>17.8892</y>
        <vx>0</vx>
        <vy>0</vy>
    </start_pos>
    <goal_pos>
        <x>-18.183</x>
        <y>18.1806</y>
        <vx>0</vx>
        <vy>0</vy>
    </goal_pos>
    <eta>0.0001</eta>
    <sig_obs>29000</sig_obs>
    <sig0>0.25515</sig0>
    <sigT>0.18272</sigT>
    <saving_prefix>/home/hzyu/git/VIMP/vimp/save/BRM_80nodes_v1/exp62</saving_prefix>
</Experiment62>
<Experiment61>
    <start_pos>
        <x>-11.7044</x>
        <y>17.8892</y>
        <vx>0</vx>
        <vy>0</vy>
    </start_pos>
    <goal_pos>
        <x>-15.2091</x>
        <y>13.085</y>
        <vx>0</vx>
        <vy>0</vy>
    </goal_pos>
    <eta>0.0001</eta>
    <sig_obs>29000</sig_obs>
    <sig0>0.25515</sig0>
    <sigT>0.10216</sigT>
    <saving_prefix>/home/hzyu/git/VIMP/vimp/save/BRM_80nodes_v1/exp61</saving_prefix>
</Experiment61>
<Experiment60>
    <start_pos>
        <x>-18.183</x>
        <y>18.1806</y>
        <vx>0</vx>
        <vy>0</vy>
    </start_pos>
    <goal_pos>
        <x>-11.7044</x>
        <y>17.8892</y>
        <vx>0</vx>
        <vy>0</vy>
    </goal_pos>
    <eta>0.0001</eta>
    <sig_obs>29000</sig_obs>
    <sig0>0.18272</sig0>
    <sigT>0.25515</sigT>
    <saving_prefix>/home/hzyu/git/VIMP/vimp/save/BRM_80nodes_v1/exp60</saving_prefix>
</Experiment60>
<Experiment71>
    <start_pos>
        <x>5.7862</x>
        <y>17.471</y>
        <vx>0</vx>
        <vy>0</vy>
    </start_pos>
    <goal_pos>
        <x>11.8936</x>
        <y>18.8317</y>
        <vx>0</vx>
        <vy>0</vy>
    </goal_pos>
    <eta>0.0001</eta>
    <sig_obs>29000</sig_obs>
    <sig0>0.17246</sig0>
    <sigT>0.065528</sigT>
    <saving_prefix>/home/hzyu/git/VIMP/vimp/save/BRM_80nodes_v1/exp71</saving_prefix>
</Experiment71>
<Experiment58>
    <start_pos>
        <x>-15.2091</x>
        <y>13.085</y>
        <vx>0</vx>
        <vy>0</vy>
    </start_pos>
    <goal_pos>
        <x>-11.7044</x>
        <y>17.8892</y>
        <vx>0</vx>
        <vy>0</vy>
    </goal_pos>
    <eta>0.0001</eta>
    <sig_obs>29000</sig_obs>
    <sig0>0.10216</sig0>
    <sigT>0.25515</sigT>
    <saving_prefix>/home/hzyu/git/VIMP/vimp/save/BRM_80nodes_v1/exp58</saving_prefix>
</Experiment58>
<Experiment57>
    <start_pos>
        <x>-15.2091</x>
        <y>13.085</y>
        <vx>0</vx>
        <vy>0</vy>
    </start_pos>
    <goal_pos>
        <x>-18.183</x>
        <y>18.1806</y>
        <vx>0</vx>
        <vy>0</vy>
    </goal_pos>
    <eta>0.0001</eta>
    <sig_obs>29000</sig_obs>
    <sig0>0.10216</sig0>
    <sigT>0.18272</sigT>
    <saving_prefix>/home/hzyu/git/VIMP/vimp/save/BRM_80nodes_v1/exp57</saving_prefix>
</Experiment57>
<Experiment56>
    <start_pos>
        <x>-15.2091</x>
        <y>13.085</y>
        <vx>0</vx>
        <vy>0</vy>
    </start_pos>
    <goal_pos>
        <x>-14.4271</x>
        <y>7.237</y>
        <vx>0</vx>
        <vy>0</vy>
    </goal_pos>
    <eta>0.0001</eta>
    <sig_obs>29000</sig_obs>
    <sig0>0.10216</sig0>
    <sigT>0.38166</sigT>
    <saving_prefix>/home/hzyu/git/VIMP/vimp/save/BRM_80nodes_v1/exp56</saving_prefix>
</Experiment56>
<Experiment55>
    <start_pos>
        <x>18.04</x>
        <y>-5.3904</y>
        <vx>0</vx>
        <vy>0</vy>
    </start_pos>
    <goal_pos>
        <x>13.7094</x>
        <y>-8.381</y>
        <vx>0</vx>
        <vy>0</vy>
    </goal_pos>
    <eta>0.0001</eta>
    <sig_obs>29000</sig_obs>
    <sig0>0.26844</sig0>
    <sigT>0.18317</sigT>
    <saving_prefix>/home/hzyu/git/VIMP/vimp/save/BRM_80nodes_v1/exp55</saving_prefix>
</Experiment55>
<Experiment54>
    <start_pos>
        <x>18.04</x>
        <y>-5.3904</y>
        <vx>0</vx>
        <vy>0</vy>
    </start_pos>
    <goal_pos>
        <x>16.7649</x>
        <y>0.37014</y>
        <vx>0</vx>
        <vy>0</vy>
    </goal_pos>
    <eta>0.0001</eta>
    <sig_obs>29000</sig_obs>
    <sig0>0.26844</sig0>
    <sigT>0.32749</sigT>
    <saving_prefix>/home/hzyu/git/VIMP/vimp/save/BRM_80nodes_v1/exp54</saving_prefix>
</Experiment54>
<Experiment53>
    <start_pos>
        <x>7.6409</x>
        <y>-1.6863</y>
        <vx>0</vx>
        <vy>0</vy>
    </start_pos>
    <goal_pos>
        <x>7.1658</x>
        <y>-6.7039</y>
        <vx>0</vx>
        <vy>0</vy>
    </goal_pos>
    <eta>0.0001</eta>
    <sig_obs>29000</sig_obs>
    <sig0>0.16593</sig0>
    <sigT>0.57366</sigT>
    <saving_prefix>/home/hzyu/git/VIMP/vimp/save/BRM_80nodes_v1/exp53</saving_prefix>
</Experiment53>
<Experiment52>
    <start_pos>
        <x>-5.0071</x>
        <y>10.1534</y>
        <vx>0</vx>
        <vy>0</vy>
    </start_pos>
    <goal_pos>
        <x>0.27386</x>
        <y>9.4536</y>
        <vx>0</vx>
        <vy>0</vy>
    </goal_pos>
    <eta>0.0001</eta>
    <sig_obs>29000</sig_obs>
    <sig0>0.06159</sig0>
    <sigT>0.10507</sigT>
    <saving_prefix>/home/hzyu/git/VIMP/vimp/save/BRM_80nodes_v1/exp52</saving_prefix>
</Experiment52>
<Experiment51>
    <start_pos>
        <x>-5.0071</x>
        <y>10.1534</y>
        <vx>0</vx>
        <vy>0</vy>
    </start_pos>
    <goal_pos>
        <x>-1.6186</x>
        <y>14.9834</y>
        <vx>0</vx>
        <vy>0</vy>
    </goal_pos>
    <eta>0.0001</eta>
    <sig_obs>29000</sig_obs>
    <sig0>0.06159</sig0>
    <sigT>0.6796</sigT>
    <saving_prefix>/home/hzyu/git/VIMP/vimp/save/BRM_80nodes_v1/exp51</saving_prefix>
</Experiment51>
<Experiment50>
    <start_pos>
        <x>-5.0071</x>
        <y>10.1534</y>
        <vx>0</vx>
        <vy>0</vy>
    </start_pos>
    <goal_pos>
        <x>-9.3175</x>
        <y>6.9111</y>
        <vx>0</vx>
        <vy>0</vy>
    </goal_pos>
    <eta>0.0001</eta>
    <sig_obs>29000</sig_obs>
    <sig0>0.06159</sig0>
    <sigT>0.28263</sigT>
    <saving_prefix>/home/hzyu/git/VIMP/vimp/save/BRM_80nodes_v1/exp50</saving_prefix>
</Experiment50>
<Experiment49>
    <start_pos>
        <x>-5.0071</x>
        <y>10.1534</y>
        <vx>0</vx>
        <vy>0</vy>
    </start_pos>
    <goal_pos>
        <x>-1.435</x>
        <y>4.4917</y>
        <vx>0</vx>
        <vy>0</vy>
    </goal_pos>
    <eta>0.0001</eta>
    <sig_obs>29000</sig_obs>
    <sig0>0.06159</sig0>
    <sigT>0.30573</sigT>
    <saving_prefix>/home/hzyu/git/VIMP/vimp/save/BRM_80nodes_v1/exp49</saving_prefix>
</Experiment49>
<Experiment48>
    <start_pos>
        <x>-9.1456</x>
        <y>-7.0836</y>
        <vx>0</vx>
        <vy>0</vy>
    </start_pos>
    <goal_pos>
        <x>-9</x>
        <y>-7</y>
        <vx>0</vx>
        <vy>0</vy>
    </goal_pos>
    <eta>0.0001</eta>
    <sig_obs>29000</sig_obs>
    <sig0>0.24794</sig0>
    <sigT>0.22641</sigT>
    <saving_prefix>/home/hzyu/git/VIMP/vimp/save/BRM_80nodes_v1/exp48</saving_prefix>
</Experiment48>
<Experiment83>
    <start_pos>
        <x>-3.2522</x>
        <y>-9.0815</y>
        <vx>0</vx>
        <vy>0</vy>
    </start_pos>
    <goal_pos>
        <x>-9</x>
        <y>-7</y>
        <vx>0</vx>
        <vy>0</vy>
    </goal_pos>
    <eta>0.0001</eta>
    <sig_obs>29000</sig_obs>
    <sig0>0.058957</sig0>
    <sigT>0.22641</sigT>
    <saving_prefix>/home/hzyu/git/VIMP/vimp/save/BRM_80nodes_v1/exp83</saving_prefix>
</Experiment83>
<Experiment94>
    <start_pos>
        <x>-9</x>
        <y>-7</y>
        <vx>0</vx>
        <vy>0</vy>
    </start_pos>
    <goal_pos>
        <x>-3.2522</x>
        <y>-9.0815</y>
        <vx>0</vx>
        <vy>0</vy>
    </goal_pos>
    <eta>0.0001</eta>
    <sig_obs>29000</sig_obs>
    <sig0>0.22641</sig0>
    <sigT>0.058957</sigT>
    <saving_prefix>/home/hzyu/git/VIMP/vimp/save/BRM_80nodes_v1/exp94</saving_prefix>
</Experiment94>
<Experiment93>
    <start_pos>
        <x>-9</x>
        <y>-7</y>
        <vx>0</vx>
        <vy>0</vy>
    </start_pos>
    <goal_pos>
        <x>-15.0401</x>
        <y>-7.3388</y>
        <vx>0</vx>
        <vy>0</vy>
    </goal_pos>
    <eta>0.0001</eta>
    <sig_obs>29000</sig_obs>
    <sig0>0.22641</sig0>
    <sigT>0.31967</sigT>
    <saving_prefix>/home/hzyu/git/VIMP/vimp/save/BRM_80nodes_v1/exp93</saving_prefix>
</Experiment93>
<Experiment92>
    <start_pos>
        <x>-9</x>
        <y>-7</y>
        <vx>0</vx>
        <vy>0</vy>
    </start_pos>
    <goal_pos>
        <x>-9.1456</x>
        <y>-7.0836</y>
        <vx>0</vx>
        <vy>0</vy>
    </goal_pos>
    <eta>0.0001</eta>
    <sig_obs>29000</sig_obs>
    <sig0>0.22641</sig0>
    <sigT>0.24794</sigT>
    <saving_prefix>/home/hzyu/git/VIMP/vimp/save/BRM_80nodes_v1/exp92</saving_prefix>
</Experiment92>
<Experiment91>
    <start_pos>
        <x>-9</x>
        <y>-7</y>
        <vx>0</vx>
        <vy>0</vy>
    </start_pos>
    <goal_pos>
        <x>-4.2101</x>
        <y>-3.7212</y>
        <vx>0</vx>
        <vy>0</vy>
    </goal_pos>
    <eta>0.0001</eta>
    <sig_obs>29000</sig_obs>
    <sig0>0.22641</sig0>
    <sigT>0.080457</sigT>
    <saving_prefix>/home/hzyu/git/VIMP/vimp/save/BRM_80nodes_v1/exp91</saving_prefix>
</Experiment91>
<Experiment90>
    <start_pos>
        <x>11.8936</x>
        <y>18.8317</y>
        <vx>0</vx>
        <vy>0</vy>
    </start_pos>
    <goal_pos>
        <x>5.7862</x>
        <y>17.471</y>
        <vx>0</vx>
        <vy>0</vy>
    </goal_pos>
    <eta>0.0001</eta>
    <sig_obs>29000</sig_obs>
    <sig0>0.065528</sig0>
    <sigT>0.17246</sigT>
    <saving_prefix>/home/hzyu/git/VIMP/vimp/save/BRM_80nodes_v1/exp90</saving_prefix>
</Experiment90>
<Experiment89>
    <start_pos>
        <x>11.8936</x>
        <y>18.8317</y>
        <vx>0</vx>
        <vy>0</vy>
    </start_pos>
    <goal_pos>
        <x>15.2844</x>
        <y>15.1209</y>
        <vx>0</vx>
        <vy>0</vy>
    </goal_pos>
    <eta>0.0001</eta>
    <sig_obs>29000</sig_obs>
    <sig0>0.065528</sig0>
    <sigT>1.1155</sigT>
    <saving_prefix>/home/hzyu/git/VIMP/vimp/save/BRM_80nodes_v1/exp89</saving_prefix>
</Experiment89>
<Experiment88>
    <start_pos>
        <x>11.8936</x>
        <y>18.8317</y>
        <vx>0</vx>
        <vy>0</vy>
    </start_pos>
    <goal_pos>
        <x>9.4765</x>
        <y>14.0824</y>
        <vx>0</vx>
        <vy>0</vy>
    </goal_pos>
    <eta>0.0001</eta>
    <sig_obs>29000</sig_obs>
    <sig0>0.065528</sig0>
    <sigT>0.053688</sigT>
    <saving_prefix>/home/hzyu/git/VIMP/vimp/save/BRM_80nodes_v1/exp88</saving_prefix>
</Experiment88>
<Experiment87>
    <start_pos>
        <x>0.27386</x>
        <y>9.4536</y>
        <vx>0</vx>
        <vy>0</vy>
    </start_pos>
    <goal_pos>
        <x>-1.6186</x>
        <y>14.9834</y>
        <vx>0</vx>
        <vy>0</vy>
    </goal_pos>
    <eta>0.0001</eta>
    <sig_obs>29000</sig_obs>
    <sig0>0.10507</sig0>
    <sigT>0.6796</sigT>
    <saving_prefix>/home/hzyu/git/VIMP/vimp/save/BRM_80nodes_v1/exp87</saving_prefix>
</Experiment87>
<Experiment86>
    <start_pos>
        <x>0.27386</x>
        <y>9.4536</y>
        <vx>0</vx>
        <vy>0</vy>
    </start_pos>
    <goal_pos>
        <x>-5.0071</x>
        <y>10.1534</y>
        <vx>0</vx>
        <vy>0</vy>
    </goal_pos>
    <eta>0.0001</eta>
    <sig_obs>29000</sig_obs>
    <sig0>0.10507</sig0>
    <sigT>0.06159</sigT>
    <saving_prefix>/home/hzyu/git/VIMP/vimp/save/BRM_80nodes_v1/exp86</saving_prefix>
</Experiment86>
<Experiment85>
    <start_pos>
        <x>0.27386</x>
        <y>9.4536</y>
        <vx>0</vx>
        <vy>0</vy>
    </start_pos>
    <goal_pos>
        <x>-1.435</x>
        <y>4.4917</y>
        <vx>0</vx>
        <vy>0</vy>
    </goal_pos>
    <eta>0.0001</eta>
    <sig_obs>29000</sig_obs>
    <sig0>0.10507</sig0>
    <sigT>0.30573</sigT>
    <saving_prefix>/home/hzyu/git/VIMP/vimp/save/BRM_80nodes_v1/exp85</saving_prefix>
</Experiment85>
<Experiment84>
    <start_pos>
        <x>0.27386</x>
        <y>9.4536</y>
        <vx>0</vx>
        <vy>0</vy>
    </start_pos>
    <goal_pos>
        <x>4.4208</x>
        <y>5.2123</y>
        <vx>0</vx>
        <vy>0</vy>
    </goal_pos>
    <eta>0.0001</eta>
    <sig_obs>29000</sig_obs>
    <sig0>0.10507</sig0>
    <sigT>0.46793</sigT>
    <saving_prefix>/home/hzyu/git/VIMP/vimp/save/BRM_80nodes_v1/exp84</saving_prefix>
</Experiment84>
<Experiment47>
    <start_pos>
        <x>-9.1456</x>
        <y>-7.0836</y>
        <vx>0</vx>
        <vy>0</vy>
    </start_pos>
    <goal_pos>
        <x>-3.2522</x>
        <y>-9.0815</y>
        <vx>0</vx>
        <vy>0</vy>
    </goal_pos>
    <eta>0.0001</eta>
    <sig_obs>29000</sig_obs>
    <sig0>0.24794</sig0>
    <sigT>0.058957</sigT>
    <saving_prefix>/home/hzyu/git/VIMP/vimp/save/BRM_80nodes_v1/exp47</saving_prefix>
</Experiment47>
<Experiment82>
    <start_pos>
        <x>-3.2522</x>
        <y>-9.0815</y>
        <vx>0</vx>
        <vy>0</vy>
    </start_pos>
    <goal_pos>
        <x>-9.1456</x>
        <y>-7.0836</y>
        <vx>0</vx>
        <vy>0</vy>
    </goal_pos>
    <eta>0.0001</eta>
    <sig_obs>29000</sig_obs>
    <sig0>0.058957</sig0>
    <sigT>0.24794</sigT>
    <saving_prefix>/home/hzyu/git/VIMP/vimp/save/BRM_80nodes_v1/exp82</saving_prefix>
</Experiment82>
<Experiment81>
    <start_pos>
        <x>-3.2522</x>
        <y>-9.0815</y>
        <vx>0</vx>
        <vy>0</vy>
    </start_pos>
    <goal_pos>
        <x>1.3555</x>
        <y>-5.6791</y>
        <vx>0</vx>
        <vy>0</vy>
    </goal_pos>
    <eta>0.0001</eta>
    <sig_obs>29000</sig_obs>
    <sig0>0.058957</sig0>
    <sigT>0.62016</sigT>
    <saving_prefix>/home/hzyu/git/VIMP/vimp/save/BRM_80nodes_v1/exp81</saving_prefix>
</Experiment81>
<Experiment80>
    <start_pos>
        <x>-3.2522</x>
        <y>-9.0815</y>
        <vx>0</vx>
        <vy>0</vy>
    </start_pos>
    <goal_pos>
        <x>-4.2101</x>
        <y>-3.7212</y>
        <vx>0</vx>
        <vy>0</vy>
    </goal_pos>
    <eta>0.0001</eta>
    <sig_obs>29000</sig_obs>
    <sig0>0.058957</sig0>
    <sigT>0.080457</sigT>
    <saving_prefix>/home/hzyu/git/VIMP/vimp/save/BRM_80nodes_v1/exp80</saving_prefix>
</Experiment80>
<Experiment79>
    <start_pos>
        <x>-6.6271</x>
        <y>18.27</y>
        <vx>0</vx>
        <vy>0</vy>
    </start_pos>
    <goal_pos>
        <x>-1.6186</x>
        <y>14.9834</y>
        <vx>0</vx>
        <vy>0</vy>
    </goal_pos>
    <eta>0.0001</eta>
    <sig_obs>29000</sig_obs>
    <sig0>0.16359</sig0>
    <sigT>0.6796</sigT>
    <saving_prefix>/home/hzyu/git/VIMP/vimp/save/BRM_80nodes_v1/exp79</saving_prefix>
</Experiment79>
<Experiment78>
    <start_pos>
        <x>-6.6271</x>
        <y>18.27</y>
        <vx>0</vx>
        <vy>0</vy>
    </start_pos>
    <goal_pos>
        <x>-11.7044</x>
        <y>17.8892</y>
        <vx>0</vx>
        <vy>0</vy>
    </goal_pos>
    <eta>0.0001</eta>
    <sig_obs>29000</sig_obs>
    <sig0>0.16359</sig0>
    <sigT>0.25515</sigT>
    <saving_prefix>/home/hzyu/git/VIMP/vimp/save/BRM_80nodes_v1/exp78</saving_prefix>
</Experiment78>
<Experiment77>
    <start_pos>
        <x>13.7094</x>
        <y>-8.381</y>
        <vx>0</vx>
        <vy>0</vy>
    </start_pos>
    <goal_pos>
        <x>18.04</x>
        <y>-5.3904</y>
        <vx>0</vx>
        <vy>0</vy>
    </goal_pos>
    <eta>0.0001</eta>
    <sig_obs>29000</sig_obs>
    <sig0>0.18317</sig0>
    <sigT>0.26844</sigT>
    <saving_prefix>/home/hzyu/git/VIMP/vimp/save/BRM_80nodes_v1/exp77</saving_prefix>
</Experiment77>
<Experiment76>
    <start_pos>
        <x>13.7094</x>
        <y>-8.381</y>
        <vx>0</vx>
        <vy>0</vy>
    </start_pos>
    <goal_pos>
        <x>7.1658</x>
        <y>-6.7039</y>
        <vx>0</vx>
        <vy>0</vy>
    </goal_pos>
    <eta>0.0001</eta>
    <sig_obs>29000</sig_obs>
    <sig0>0.18317</sig0>
    <sigT>0.57366</sigT>
    <saving_prefix>/home/hzyu/git/VIMP/vimp/save/BRM_80nodes_v1/exp76</saving_prefix>
</Experiment76>
<Experiment75>
    <start_pos>
        <x>-17.84</x>
        <y>-2.836</y>
        <vx>0</vx>
        <vy>0</vy>
    </start_pos>
    <goal_pos>
        <x>-18.4734</x>
        <y>2.9431</y>
        <vx>0</vx>
        <vy>0</vy>
    </goal_pos>
    <eta>0.0001</eta>
    <sig_obs>29000</sig_obs>
    <sig0>0.26844</sig0>
    <sigT>0.12298</sigT>
    <saving_prefix>/home/hzyu/git/VIMP/vimp/save/BRM_80nodes_v1/exp75</saving_prefix>
</Experiment75>
<Experiment74>
    <start_pos>
        <x>-17.84</x>
        <y>-2.836</y>
        <vx>0</vx>
        <vy>0</vy>
    </start_pos>
    <goal_pos>
        <x>-15.0401</x>
        <y>-7.3388</y>
        <vx>0</vx>
        <vy>0</vy>
    </goal_pos>
    <eta>0.0001</eta>
    <sig_obs>29000</sig_obs>
    <sig0>0.26844</sig0>
    <sigT>0.31967</sigT>
    <saving_prefix>/home/hzyu/git/VIMP/vimp/save/BRM_80nodes_v1/exp74</saving_prefix>
</Experiment74>
<Experiment73>
    <start_pos>
        <x>-18.4734</x>
        <y>2.9431</y>
        <vx>0</vx>
        <vy>0</vy>
    </start_pos>
    <goal_pos>
        <x>-17.84</x>
        <y>-2.836</y>
        <vx>0</vx>
        <vy>0</vy>
    </goal_pos>
    <eta>0.0001</eta>
    <sig_obs>29000</sig_obs>
    <sig0>0.12298</sig0>
    <sigT>0.26844</sigT>
    <saving_prefix>/home/hzyu/git/VIMP/vimp/save/BRM_80nodes_v1/exp73</saving_prefix>
</Experiment73>
<Experiment72>
    <start_pos>
        <x>-18.4734</x>
        <y>2.9431</y>
        <vx>0</vx>
        <vy>0</vy>
    </start_pos>
    <goal_pos>
        <x>-14.4271</x>
        <y>7.237</y>
        <vx>0</vx>
        <vy>0</vy>
    </goal_pos>
    <eta>0.0001</eta>
    <sig_obs>29000</sig_obs>
    <sig0>0.12298</sig0>
    <sigT>0.38166</sigT>
    <saving_prefix>/home/hzyu/git/VIMP/vimp/save/BRM_80nodes_v1/exp72</saving_prefix>
</Experiment72>
<Experiment12>
    <start_pos>
        <x>-1.435</x>
        <y>4.4917</y>
        <vx>0</vx>
        <vy>0</vy>
    </start_pos>
    <goal_pos>
        <x>-5.0071</x>
        <y>10.1534</y>
        <vx>0</vx>
        <vy>0</vy>
    </goal_pos>
    <eta>0.0001</eta>
    <sig_obs>29000</sig_obs>
    <sig0>0.30573</sig0>
    <sigT>0.06159</sigT>
    <saving_prefix>/home/hzyu/git/VIMP/vimp/save/BRM_80nodes_v1/exp12</saving_prefix>
</Experiment12>
<Experiment23>
    <start_pos>
        <x>9.4765</x>
        <y>14.0824</y>
        <vx>0</vx>
        <vy>0</vy>
    </start_pos>
    <goal_pos>
        <x>11.8936</x>
        <y>18.8317</y>
        <vx>0</vx>
        <vy>0</vy>
    </goal_pos>
    <eta>0.0001</eta>
    <sig_obs>29000</sig_obs>
    <sig0>0.053688</sig0>
    <sigT>0.065528</sigT>
    <saving_prefix>/home/hzyu/git/VIMP/vimp/save/BRM_80nodes_v1/exp23</saving_prefix>
</Experiment23>
<Experiment22>
    <start_pos>
        <x>9.4765</x>
        <y>14.0824</y>
        <vx>0</vx>
        <vy>0</vy>
    </start_pos>
    <goal_pos>
        <x>5.7862</x>
        <y>17.471</y>
        <vx>0</vx>
        <vy>0</vy>
    </goal_pos>
    <eta>0.0001</eta>
    <sig_obs>29000</sig_obs>
    <sig0>0.053688</sig0>
    <sigT>0.17246</sigT>
    <saving_prefix>/home/hzyu/git/VIMP/vimp/save/BRM_80nodes_v1/exp22</saving_prefix>
</Experiment22>
<Experiment21>
    <start_pos>
        <x>9.4765</x>
        <y>14.0824</y>
        <vx>0</vx>
        <vy>0</vy>
    </start_pos>
    <goal_pos>
        <x>15.2844</x>
        <y>15.1209</y>
        <vx>0</vx>
        <vy>0</vy>
    </goal_pos>
    <eta>0.0001</eta>
    <sig_obs>29000</sig_obs>
    <sig0>0.053688</sig0>
    <sigT>1.1155</sigT>
    <saving_prefix>/home/hzyu/git/VIMP/vimp/save/BRM_80nodes_v1/exp21</saving_prefix>
</Experiment21>
<Experiment20>
    <start_pos>
        <x>9.4765</x>
        <y>14.0824</y>
        <vx>0</vx>
        <vy>0</vy>
    </start_pos>
    <goal_pos>
        <x>9.5185</x>
        <y>8.1826</y>
        <vx>0</vx>
        <vy>0</vy>
    </goal_pos>
    <eta>0.0001</eta>
    <sig_obs>29000</sig_obs>
    <sig0>0.053688</sig0>
    <sigT>0.058967</sigT>
    <saving_prefix>/home/hzyu/git/VIMP/vimp/save/BRM_80nodes_v1/exp20</saving_prefix>
</Experiment20>
<Experiment19>
    <start_pos>
        <x>-9.3175</x>
        <y>6.9111</y>
        <vx>0</vx>
        <vy>0</vy>
    </start_pos>
    <goal_pos>
        <x>-5.0071</x>
        <y>10.1534</y>
        <vx>0</vx>
        <vy>0</vy>
    </goal_pos>
    <eta>0.0001</eta>
    <sig_obs>29000</sig_obs>
    <sig0>0.28263</sig0>
    <sigT>0.06159</sigT>
    <saving_prefix>/home/hzyu/git/VIMP/vimp/save/BRM_80nodes_v1/exp19</saving_prefix>
</Experiment19>
<Experiment18>
    <start_pos>
        <x>-9.3175</x>
        <y>6.9111</y>
        <vx>0</vx>
        <vy>0</vy>
    </start_pos>
    <goal_pos>
        <x>-14.4271</x>
        <y>7.237</y>
        <vx>0</vx>
        <vy>0</vy>
    </goal_pos>
    <eta>0.0001</eta>
    <sig_obs>29000</sig_obs>
    <sig0>0.28263</sig0>
    <sigT>0.38166</sigT>
    <saving_prefix>/home/hzyu/git/VIMP/vimp/save/BRM_80nodes_v1/exp18</saving_prefix>
</Experiment18>
<Experiment17>
    <start_pos>
        <x>-9.3175</x>
        <y>6.9111</y>
        <vx>0</vx>
        <vy>0</vy>
    </start_pos>
    <goal_pos>
        <x>-6.6147</x>
        <y>1.6666</y>
        <vx>0</vx>
        <vy>0</vy>
    </goal_pos>
    <eta>0.0001</eta>
    <sig_obs>29000</sig_obs>
    <sig0>0.28263</sig0>
    <sigT>0.22273</sigT>
    <saving_prefix>/home/hzyu/git/VIMP/vimp/save/BRM_80nodes_v1/exp17</saving_prefix>
</Experiment17>
<Experiment16>
    <start_pos>
        <x>-6.6147</x>
        <y>1.6666</y>
        <vx>0</vx>
        <vy>0</vy>
    </start_pos>
    <goal_pos>
        <x>-4.2101</x>
        <y>-3.7212</y>
        <vx>0</vx>
        <vy>0</vy>
    </goal_pos>
    <eta>0.0001</eta>
    <sig_obs>29000</sig_obs>
    <sig0>0.22273</sig0>
    <sigT>0.080457</sigT>
    <saving_prefix>/home/hzyu/git/VIMP/vimp/save/BRM_80nodes_v1/exp16</saving_prefix>
</Experiment16>
<Experiment15>
    <start_pos>
        <x>-6.6147</x>
        <y>1.6666</y>
        <vx>0</vx>
        <vy>0</vy>
    </start_pos>
    <goal_pos>
        <x>-9.3175</x>
        <y>6.9111</y>
        <vx>0</vx>
        <vy>0</vy>
    </goal_pos>
    <eta>0.0001</eta>
    <sig_obs>29000</sig_obs>
    <sig0>0.22273</sig0>
    <sigT>0.28263</sigT>
    <saving_prefix>/home/hzyu/git/VIMP/vimp/save/BRM_80nodes_v1/exp15</saving_prefix>
</Experiment15>
<Experiment14>
    <start_pos>
        <x>-6.6147</x>
        <y>1.6666</y>
        <vx>0</vx>
        <vy>0</vy>
    </start_pos>
    <goal_pos>
        <x>-1.435</x>
        <y>4.4917</y>
        <vx>0</vx>
        <vy>0</vy>
    </goal_pos>
    <eta>0.0001</eta>
    <sig_obs>29000</sig_obs>
    <sig0>0.22273</sig0>
    <sigT>0.30573</sigT>
    <saving_prefix>/home/hzyu/git/VIMP/vimp/save/BRM_80nodes_v1/exp14</saving_prefix>
</Experiment14>
<Experiment13>
    <start_pos>
        <x>-1.435</x>
        <y>4.4917</y>
        <vx>0</vx>
        <vy>0</vy>
    </start_pos>
    <goal_pos>
        <x>0.27386</x>
        <y>9.4536</y>
        <vx>0</vx>
        <vy>0</vy>
    </goal_pos>
    <eta>0.0001</eta>
    <sig_obs>29000</sig_obs>
    <sig0>0.30573</sig0>
    <sigT>0.10507</sigT>
    <saving_prefix>/home/hzyu/git/VIMP/vimp/save/BRM_80nodes_v1/exp13</saving_prefix>
</Experiment13>
<Experiment24>
    <start_pos>
        <x>16.7649</x>
        <y>0.37014</y>
        <vx>0</vx>
        <vy>0</vy>
    </start_pos>
    <goal_pos>
        <x>15</x>
        <y>6</y>
        <vx>0</vx>
        <vy>0</vy>
    </goal_pos>
    <eta>0.0001</eta>
    <sig_obs>29000</sig_obs>
    <sig0>0.32749</sig0>
    <sigT>0.10899</sigT>
    <saving_prefix>/home/hzyu/git/VIMP/vimp/save/BRM_80nodes_v1/exp24</saving_prefix>
</Experiment24>
<Experiment11>
    <start_pos>
        <x>-1.435</x>
        <y>4.4917</y>
        <vx>0</vx>
        <vy>0</vy>
    </start_pos>
    <goal_pos>
        <x>-6.6147</x>
        <y>1.6666</y>
        <vx>0</vx>
        <vy>0</vy>
    </goal_pos>
    <eta>0.0001</eta>
    <sig_obs>29000</sig_obs>
    <sig0>0.30573</sig0>
    <sigT>0.22273</sigT>
    <saving_prefix>/home/hzyu/git/VIMP/vimp/save/BRM_80nodes_v1/exp11</saving_prefix>
</Experiment11>
<Experiment10>
    <start_pos>
        <x>-1.435</x>
        <y>4.4917</y>
        <vx>0</vx>
        <vy>0</vy>
    </start_pos>
    <goal_pos>
        <x>4.4208</x>
        <y>5.2123</y>
        <vx>0</vx>
        <vy>0</vy>
    </goal_pos>
    <eta>0.0001</eta>
    <sig_obs>29000</sig_obs>
    <sig0>0.30573</sig0>
    <sigT>0.46793</sigT>
    <saving_prefix>/home/hzyu/git/VIMP/vimp/save/BRM_80nodes_v1/exp10</saving_prefix>
</Experiment10>
<Experiment9>
    <start_pos>
        <x>4.4208</x>
        <y>5.2123</y>
        <vx>0</vx>
        <vy>0</vy>
    </start_pos>
    <goal_pos>
        <x>0.27386</x>
        <y>9.4536</y>
        <vx>0</vx>
        <vy>0</vy>
    </goal_pos>
    <eta>0.0001</eta>
    <sig_obs>29000</sig_obs>
    <sig0>0.46793</sig0>
    <sigT>0.10507</sigT>
    <saving_prefix>/home/hzyu/git/VIMP/vimp/save/BRM_80nodes_v1/exp9</saving_prefix>
</Experiment9>
<Experiment8>
    <start_pos>
        <x>4.4208</x>
        <y>5.2123</y>
        <vx>0</vx>
        <vy>0</vy>
    </start_pos>
    <goal_pos>
        <x>-1.435</x>
        <y>4.4917</y>
        <vx>0</vx>
        <vy>0</vy>
    </goal_pos>
    <eta>0.0001</eta>
    <sig_obs>29000</sig_obs>
    <sig0>0.46793</sig0>
    <sigT>0.30573</sigT>
    <saving_prefix>/home/hzyu/git/VIMP/vimp/save/BRM_80nodes_v1/exp8</saving_prefix>
</Experiment8>
<Experiment7>
    <start_pos>
        <x>4.4208</x>
        <y>5.2123</y>
        <vx>0</vx>
        <vy>0</vy>
    </start_pos>
    <goal_pos>
        <x>9.5185</x>
        <y>8.1826</y>
        <vx>0</vx>
        <vy>0</vy>
    </goal_pos>
    <eta>0.0001</eta>
    <sig_obs>29000</sig_obs>
    <sig0>0.46793</sig0>
    <sigT>0.058967</sigT>
    <saving_prefix>/home/hzyu/git/VIMP/vimp/save/BRM_80nodes_v1/exp7</saving_prefix>
</Experiment7>
<Experiment6>
    <start_pos>
        <x>9.5185</x>
        <y>8.1826</y>
        <vx>0</vx>
        <vy>0</vy>
    </start_pos>
    <goal_pos>
        <x>9.4765</x>
        <y>14.0824</y>
        <vx>0</vx>
        <vy>0</vy>
    </goal_pos>
    <eta>0.0001</eta>
    <sig_obs>29000</sig_obs>
    <sig0>0.058967</sig0>
    <sigT>0.053688</sigT>
    <saving_prefix>/home/hzyu/git/VIMP/vimp/save/BRM_80nodes_v1/exp6</saving_prefix>
</Experiment6>
<Experiment5>
    <start_pos>
        <x>9.5185</x>
        <y>8.1826</y>
        <vx>0</vx>
        <vy>0</vy>
    </start_pos>
    <goal_pos>
        <x>4.4208</x>
        <y>5.2123</y>
        <vx>0</vx>
        <vy>0</vy>
    </goal_pos>
    <eta>0.0001</eta>
    <sig_obs>29000</sig_obs>
    <sig0>0.058967</sig0>
    <sigT>0.46793</sigT>
    <saving_prefix>/home/hzyu/git/VIMP/vimp/save/BRM_80nodes_v1/exp5</saving_prefix>
</Experiment5>
<Experiment4>
    <start_pos>
        <x>9.5185</x>
        <y>8.1826</y>
        <vx>0</vx>
        <vy>0</vy>
    </start_pos>
    <goal_pos>
        <x>15</x>
        <y>6</y>
        <vx>0</vx>
        <vy>0</vy>
    </goal_pos>
    <eta>0.0001</eta>
    <sig_obs>29000</sig_obs>
    <sig0>0.058967</sig0>
    <sigT>0.10899</sigT>
    <saving_prefix>/home/hzyu/git/VIMP/vimp/save/BRM_80nodes_v1/exp4</saving_prefix>
</Experiment4>
<Experiment3>
    <start_pos>
        <x>15</x>
        <y>6</y>
        <vx>0</vx>
        <vy>0</vy>
    </start_pos>
    <goal_pos>
        <x>19.0554</x>
        <y>10.8455</y>
        <vx>0</vx>
        <vy>0</vy>
    </goal_pos>
    <eta>0.0001</eta>
    <sig_obs>29000</sig_obs>
    <sig0>0.10899</sig0>
    <sigT>0.062354</sigT>
    <saving_prefix>/home/hzyu/git/VIMP/vimp/save/BRM_80nodes_v1/exp3</saving_prefix>
</Experiment3>
<Experiment2>
    <start_pos>
        <x>15</x>
        <y>6</y>
        <vx>0</vx>
        <vy>0</vy>
    </start_pos>
    <goal_pos>
        <x>16.7649</x>
        <y>0.37014</y>
        <vx>0</vx>
        <vy>0</vy>
    </goal_pos>
    <eta>0.0001</eta>
    <sig_obs>29000</sig_obs>
    <sig0>0.10899</sig0>
    <sigT>0.32749</sigT>
    <saving_prefix>/home/hzyu/git/VIMP/vimp/save/BRM_80nodes_v1/exp2</saving_prefix>
</Experiment2>
<Experiment1>
    <start_pos>
        <x>15</x>
        <y>6</y>
        <vx>0</vx>
        <vy>0</vy>
    </start_pos>
    <goal_pos>
        <x>9.5185</x>
        <y>8.1826</y>
        <vx>0</vx>
        <vy>0</vy>
    </goal_pos>
    <eta>0.0001</eta>
    <sig_obs>29000</sig_obs>
    <sig0>0.10899</sig0>
    <sigT>0.058967</sigT>
    <saving_prefix>/home/hzyu/git/VIMP/vimp/save/BRM_80nodes_v1/exp1</saving_prefix>
</Experiment1>
<Experiment35>
    <start_pos>
        <x>1.3555</x>
        <y>-5.6791</y>
        <vx>0</vx>
        <vy>0</vy>
    </start_pos>
    <goal_pos>
        <x>7.1658</x>
        <y>-6.7039</y>
        <vx>0</vx>
        <vy>0</vy>
    </goal_pos>
    <eta>0.0001</eta>
    <sig_obs>29000</sig_obs>
    <sig0>0.62016</sig0>
    <sigT>0.57366</sigT>
    <saving_prefix>/home/hzyu/git/VIMP/vimp/save/BRM_80nodes_v1/exp35</saving_prefix>
</Experiment35>
<Experiment46>
    <start_pos>
        <x>-9.1456</x>
        <y>-7.0836</y>
        <vx>0</vx>
        <vy>0</vy>
    </start_pos>
    <goal_pos>
        <x>-15.0401</x>
        <y>-7.3388</y>
        <vx>0</vx>
        <vy>0</vy>
    </goal_pos>
    <eta>0.0001</eta>
    <sig_obs>29000</sig_obs>
    <sig0>0.24794</sig0>
    <sigT>0.31967</sigT>
    <saving_prefix>/home/hzyu/git/VIMP/vimp/save/BRM_80nodes_v1/exp46</saving_prefix>
</Experiment46>
<Experiment45>
    <start_pos>
        <x>-9.1456</x>
        <y>-7.0836</y>
        <vx>0</vx>
        <vy>0</vy>
    </start_pos>
    <goal_pos>
        <x>-4.2101</x>
        <y>-3.7212</y>
        <vx>0</vx>
        <vy>0</vy>
    </goal_pos>
    <eta>0.0001</eta>
    <sig_obs>29000</sig_obs>
    <sig0>0.24794</sig0>
    <sigT>0.080457</sigT>
    <saving_prefix>/home/hzyu/git/VIMP/vimp/save/BRM_80nodes_v1/exp45</saving_prefix>
</Experiment45>
<Experiment44>
    <start_pos>
        <x>19.0554</x>
        <y>10.8455</y>
        <vx>0</vx>
        <vy>0</vy>
    </start_pos>
    <goal_pos>
        <x>15.2844</x>
        <y>15.1209</y>
        <vx>0</vx>
        <vy>0</vy>
    </goal_pos>
    <eta>0.0001</eta>
    <sig_obs>29000</sig_obs>
    <sig0>0.062354</sig0>
    <sigT>1.1155</sigT>
    <saving_prefix>/home/hzyu/git/VIMP/vimp/save/BRM_80nodes_v1/exp44</saving_prefix>
</Experiment44>
<Experiment43>
    <start_pos>
        <x>19.0554</x>
        <y>10.8455</y>
        <vx>0</vx>
        <vy>0</vy>
    </start_pos>
    <goal_pos>
        <x>15</x>
        <y>6</y>
        <vx>0</vx>
        <vy>0</vy>
    </goal_pos>
    <eta>0.0001</eta>
    <sig_obs>29000</sig_obs>
    <sig0>0.062354</sig0>
    <sigT>0.10899</sigT>
    <saving_prefix>/home/hzyu/git/VIMP/vimp/save/BRM_80nodes_v1/exp43</saving_prefix>
</Experiment43>
<Experiment42>
    <start_pos>
        <x>7.1658</x>
        <y>-6.7039</y>
        <vx>0</vx>
        <vy>0</vy>
    </start_pos>
    <goal_pos>
        <x>13.7094</x>
        <y>-8.381</y>
        <vx>0</vx>
        <vy>0</vy>
    </goal_pos>
    <eta>0.0001</eta>
    <sig_obs>29000</sig_obs>
    <sig0>0.57366</sig0>
    <sigT>0.18317</sigT>
    <saving_prefix>/home/hzyu/git/VIMP/vimp/save/BRM_80nodes_v1/exp42</saving_prefix>
</Experiment42>
<Experiment41>
    <start_pos>
        <x>7.1658</x>
        <y>-6.7039</y>
        <vx>0</vx>
        <vy>0</vy>
    </start_pos>
    <goal_pos>
        <x>7.6409</x>
        <y>-1.6863</y>
        <vx>0</vx>
        <vy>0</vy>
    </goal_pos>
    <eta>0.0001</eta>
    <sig_obs>29000</sig_obs>
    <sig0>0.57366</sig0>
    <sigT>0.16593</sigT>
    <saving_prefix>/home/hzyu/git/VIMP/vimp/save/BRM_80nodes_v1/exp41</saving_prefix>
</Experiment41>
<Experiment40>
    <start_pos>
        <x>7.1658</x>
        <y>-6.7039</y>
        <vx>0</vx>
        <vy>0</vy>
    </start_pos>
    <goal_pos>
        <x>1.3555</x>
        <y>-5.6791</y>
        <vx>0</vx>
        <vy>0</vy>
    </goal_pos>
    <eta>0.0001</eta>
    <sig_obs>29000</sig_obs>
    <sig0>0.57366</sig0>
    <sigT>0.62016</sigT>
    <saving_prefix>/home/hzyu/git/VIMP/vimp/save/BRM_80nodes_v1/exp40</saving_prefix>
</Experiment40>
<Experiment39>
    <start_pos>
        <x>-14.4271</x>
        <y>7.237</y>
        <vx>0</vx>
        <vy>0</vy>
    </start_pos>
    <goal_pos>
        <x>-18.4734</x>
        <y>2.9431</y>
        <vx>0</vx>
        <vy>0</vy>
    </goal_pos>
    <eta>0.0001</eta>
    <sig_obs>29000</sig_obs>
    <sig0>0.38166</sig0>
    <sigT>0.12298</sigT>
    <saving_prefix>/home/hzyu/git/VIMP/vimp/save/BRM_80nodes_v1/exp39</saving_prefix>
</Experiment39>
<Experiment38>
    <start_pos>
        <x>-14.4271</x>
        <y>7.237</y>
        <vx>0</vx>
        <vy>0</vy>
    </start_pos>
    <goal_pos>
        <x>-15.2091</x>
        <y>13.085</y>
        <vx>0</vx>
        <vy>0</vy>
    </goal_pos>
    <eta>0.0001</eta>
    <sig_obs>29000</sig_obs>
    <sig0>0.38166</sig0>
    <sigT>0.10216</sigT>
    <saving_prefix>/home/hzyu/git/VIMP/vimp/save/BRM_80nodes_v1/exp38</saving_prefix>
</Experiment38>
<Experiment37>
    <start_pos>
        <x>-14.4271</x>
        <y>7.237</y>
        <vx>0</vx>
        <vy>0</vy>
    </start_pos>
    <goal_pos>
        <x>-9.3175</x>
        <y>6.9111</y>
        <vx>0</vx>
        <vy>0</vy>
    </goal_pos>
    <eta>0.0001</eta>
    <sig_obs>29000</sig_obs>
    <sig0>0.38166</sig0>
    <sigT>0.28263</sigT>
    <saving_prefix>/home/hzyu/git/VIMP/vimp/save/BRM_80nodes_v1/exp37</saving_prefix>
</Experiment37>
<Experiment36>
    <start_pos>
        <x>1.3555</x>
        <y>-5.6791</y>
        <vx>0</vx>
        <vy>0</vy>
    </start_pos>
    <goal_pos>
        <x>-3.2522</x>
        <y>-9.0815</y>
        <vx>0</vx>
        <vy>0</vy>
    </goal_pos>
    <eta>0.0001</eta>
    <sig_obs>29000</sig_obs>
    <sig0>0.62016</sig0>
    <sigT>0.058957</sigT>
    <saving_prefix>/home/hzyu/git/VIMP/vimp/save/BRM_80nodes_v1/exp36</saving_prefix>
</Experiment36>
<Commons>
    <eps>0.01</eps>
    <eps_sdf>0.6</eps_sdf>
    <radius>1.5</radius>
    <total_time>1.5</total_time>
    <nt>50</nt>
    <sig0>0.01</sig0>
    <sigT>0.05</sigT>
    <eta>0.0001</eta>
    <stop_err>0.001</stop_err>
    <max_iter>50</max_iter>
    <map_name>2dpr_map2</map_name>
    <sig_obs>20000</sig_obs>
    <backtracking_ratio>0.7</backtracking_ratio>
    <max_n_backtracking>3</max_n_backtracking>
</Commons>
<Experiment34>
    <start_pos>
        <x>1.3555</x>
        <y>-5.6791</y>
        <vx>0</vx>
        <vy>0</vy>
    </start_pos>
    <goal_pos>
        <x>-4.2101</x>
        <y>-3.7212</y>
        <vx>0</vx>
        <vy>0</vy>
    </goal_pos>
    <eta>0.0001</eta>
    <sig_obs>29000</sig_obs>
    <sig0>0.62016</sig0>
    <sigT>0.080457</sigT>
    <saving_prefix>/home/hzyu/git/VIMP/vimp/save/BRM_80nodes_v1/exp34</saving_prefix>
</Experiment34>
<Experiment33>
    <start_pos>
        <x>15.2844</x>
        <y>15.1209</y>
        <vx>0</vx>
        <vy>0</vy>
    </start_pos>
    <goal_pos>
        <x>11.8936</x>
        <y>18.8317</y>
        <vx>0</vx>
        <vy>0</vy>
    </goal_pos>
    <eta>0.0001</eta>
    <sig_obs>29000</sig_obs>
    <sig0>1.1155</sig0>
    <sigT>0.065528</sigT>
    <saving_prefix>/home/hzyu/git/VIMP/vimp/save/BRM_80nodes_v1/exp33</saving_prefix>
</Experiment33>
<Experiment32>
    <start_pos>
        <x>15.2844</x>
        <y>15.1209</y>
        <vx>0</vx>
        <vy>0</vy>
    </start_pos>
    <goal_pos>
        <x>19.0554</x>
        <y>10.8455</y>
        <vx>0</vx>
        <vy>0</vy>
    </goal_pos>
    <eta>0.0001</eta>
    <sig_obs>29000</sig_obs>
    <sig0>1.1155</sig0>
    <sigT>0.062354</sigT>
    <saving_prefix>/home/hzyu/git/VIMP/vimp/save/BRM_80nodes_v1/exp32</saving_prefix>
</Experiment32>
<Experiment31>
    <start_pos>
        <x>15.2844</x>
        <y>15.1209</y>
        <vx>0</vx>
        <vy>0</vy>
    </start_pos>
    <goal_pos>
        <x>9.4765</x>
        <y>14.0824</y>
        <vx>0</vx>
        <vy>0</vy>
    </goal_pos>
    <eta>0.0001</eta>
    <sig_obs>29000</sig_obs>
    <sig0>1.1155</sig0>
    <sigT>0.053688</sigT>
    <saving_prefix>/home/hzyu/git/VIMP/vimp/save/BRM_80nodes_v1/exp31</saving_prefix>
</Experiment31>
<Experiment30>
    <start_pos>
        <x>-4.2101</x>
        <y>-3.7212</y>
        <vx>0</vx>
        <vy>0</vy>
    </start_pos>
    <goal_pos>
        <x>-9</x>
        <y>-7</y>
        <vx>0</vx>
        <vy>0</vy>
    </goal_pos>
    <eta>0.0001</eta>
    <sig_obs>29000</sig_obs>
    <sig0>0.080457</sig0>
    <sigT>0.22641</sigT>
    <saving_prefix>/home/hzyu/git/VIMP/vimp/save/BRM_80nodes_v1/exp30</saving_prefix>
</Experiment30>
<Experiment29>
    <start_pos>
        <x>-4.2101</x>
        <y>-3.7212</y>
        <vx>0</vx>
        <vy>0</vy>
    </start_pos>
    <goal_pos>
        <x>-3.2522</x>
        <y>-9.0815</y>
        <vx>0</vx>
        <vy>0</vy>
    </goal_pos>
    <eta>0.0001</eta>
    <sig_obs>29000</sig_obs>
    <sig0>0.080457</sig0>
    <sigT>0.058957</sigT>
    <saving_prefix>/home/hzyu/git/VIMP/vimp/save/BRM_80nodes_v1/exp29</saving_prefix>
</Experiment29>
<Experiment28>
    <start_pos>
        <x>-4.2101</x>
        <y>-3.7212</y>
        <vx>0</vx>
        <vy>0</vy>
    </start_pos>
    <goal_pos>
        <x>-9.1456</x>
        <y>-7.0836</y>
        <vx>0</vx>
        <vy>0</vy>
    </goal_pos>
    <eta>0.0001</eta>
    <sig_obs>29000</sig_obs>
    <sig0>0.080457</sig0>
    <sigT>0.24794</sigT>
    <saving_prefix>/home/hzyu/git/VIMP/vimp/save/BRM_80nodes_v1/exp28</saving_prefix>
</Experiment28>
<Experiment27>
    <start_pos>
        <x>-4.2101</x>
        <y>-3.7212</y>
        <vx>0</vx>
        <vy>0</vy>
    </start_pos>
    <goal_pos>
        <x>1.3555</x>
        <y>-5.6791</y>
        <vx>0</vx>
        <vy>0</vy>
    </goal_pos>
    <eta>0.0001</eta>
    <sig_obs>29000</sig_obs>
    <sig0>0.080457</sig0>
    <sigT>0.62016</sigT>
    <saving_prefix>/home/hzyu/git/VIMP/vimp/save/BRM_80nodes_v1/exp27</saving_prefix>
</Experiment27>
<Experiment26>
    <start_pos>
        <x>-4.2101</x>
        <y>-3.7212</y>
        <vx>0</vx>
        <vy>0</vy>
    </start_pos>
    <goal_pos>
        <x>-6.6147</x>
        <y>1.6666</y>
        <vx>0</vx>
        <vy>0</vy>
    </goal_pos>
    <eta>0.0001</eta>
    <sig_obs>29000</sig_obs>
    <sig0>0.080457</sig0>
    <sigT>0.22273</sigT>
    <saving_prefix>/home/hzyu/git/VIMP/vimp/save/BRM_80nodes_v1/exp26</saving_prefix>
</Experiment26>
<Experiment25>
    <start_pos>
        <x>16.7649</x>
        <y>0.37014</y>
        <vx>0</vx>
        <vy>0</vy>
    </start_pos>
    <goal_pos>
        <x>18.04</x>
        <y>-5.3904</y>
        <vx>0</vx>
        <vy>0</vy>
    </goal_pos>
    <eta>0.0001</eta>
    <sig_obs>29000</sig_obs>
    <sig0>0.32749</sig0>
    <sigT>0.26844</sigT>
    <saving_prefix>/home/hzyu/git/VIMP/vimp/save/BRM_80nodes_v1/exp25</saving_prefix>
</Experiment25>
