
<Experiment47>
    <start_pos>
        <x>5.068</x>
        <y>18.2106</y>
        <vx>0</vx>
        <vy>0</vy>
    </start_pos>
    <goal_pos>
        <x>10.4108</x>
        <y>16.4603</y>
        <vx>0</vx>
        <vy>0</vy>
    </goal_pos>
    <eta>0.0001</eta>
    <sig_obs>29000</sig_obs>
    <sig0>0.21793</sig0>
    <sigT>0.33448</sigT>
    <saving_prefix>/home/zchen927/Documents/VIMP/vimp/save/BRM_20nodes_v1/exp47</saving_prefix>
</Experiment47>
<Experiment32>
    <start_pos>
        <x>-17.517</x>
        <y>2.3258</y>
        <vx>0</vx>
        <vy>0</vy>
    </start_pos>
    <goal_pos>
        <x>-17.7997</x>
        <y>-4.4425</y>
        <vx>0</vx>
        <vy>0</vy>
    </goal_pos>
    <eta>0.0001</eta>
    <sig_obs>29000</sig_obs>
    <sig0>0.35097</sig0>
    <sigT>0.34518</sigT>
    <saving_prefix>/home/zchen927/Documents/VIMP/vimp/save/BRM_20nodes_v1/exp32</saving_prefix>
</Experiment32>
<Experiment33>
    <start_pos>
        <x>-6.396</x>
        <y>-3.5565</y>
        <vx>0</vx>
        <vy>0</vy>
    </start_pos>
    <goal_pos>
        <x>-5.5944</x>
        <y>4.3028</y>
        <vx>0</vx>
        <vy>0</vy>
    </goal_pos>
    <eta>0.0001</eta>
    <sig_obs>29000</sig_obs>
    <sig0>0.34647</sig0>
    <sigT>0.67903</sigT>
    <saving_prefix>/home/zchen927/Documents/VIMP/vimp/save/BRM_20nodes_v1/exp33</saving_prefix>
</Experiment33>
<Experiment34>
    <start_pos>
        <x>-6.396</x>
        <y>-3.5565</y>
        <vx>0</vx>
        <vy>0</vy>
    </start_pos>
    <goal_pos>
        <x>0.90345</x>
        <y>-6.471</y>
        <vx>0</vx>
        <vy>0</vy>
    </goal_pos>
    <eta>0.0001</eta>
    <sig_obs>29000</sig_obs>
    <sig0>0.34647</sig0>
    <sigT>0.77462</sigT>
    <saving_prefix>/home/zchen927/Documents/VIMP/vimp/save/BRM_20nodes_v1/exp34</saving_prefix>
</Experiment34>
<Experiment35>
    <start_pos>
        <x>-6.396</x>
        <y>-3.5565</y>
        <vx>0</vx>
        <vy>0</vy>
    </start_pos>
    <goal_pos>
        <x>-10.1761</x>
        <y>-7.3727</y>
        <vx>0</vx>
        <vy>0</vy>
    </goal_pos>
    <eta>0.0001</eta>
    <sig_obs>29000</sig_obs>
    <sig0>0.34647</sig0>
    <sigT>0.40724</sigT>
    <saving_prefix>/home/zchen927/Documents/VIMP/vimp/save/BRM_20nodes_v1/exp35</saving_prefix>
</Experiment35>
<Experiment36>
    <start_pos>
        <x>-8.2745</x>
        <y>18.6513</y>
        <vx>0</vx>
        <vy>0</vy>
    </start_pos>
    <goal_pos>
        <x>-16</x>
        <y>17</y>
        <vx>0</vx>
        <vy>0</vy>
    </goal_pos>
    <eta>0.0001</eta>
    <sig_obs>29000</sig_obs>
    <sig0>0.11385</sig0>
    <sigT>0.67634</sigT>
    <saving_prefix>/home/zchen927/Documents/VIMP/vimp/save/BRM_20nodes_v1/exp36</saving_prefix>
</Experiment36>
<Experiment37>
    <start_pos>
        <x>-8.2745</x>
        <y>18.6513</y>
        <vx>0</vx>
        <vy>0</vy>
    </start_pos>
    <goal_pos>
        <x>-3.1484</x>
        <y>18.0263</y>
        <vx>0</vx>
        <vy>0</vy>
    </goal_pos>
    <eta>0.0001</eta>
    <sig_obs>29000</sig_obs>
    <sig0>0.11385</sig0>
    <sigT>0.27141</sigT>
    <saving_prefix>/home/zchen927/Documents/VIMP/vimp/save/BRM_20nodes_v1/exp37</saving_prefix>
</Experiment37>
<Experiment38>
    <start_pos>
        <x>18.1186</x>
        <y>-5.0753</y>
        <vx>0</vx>
        <vy>0</vy>
    </start_pos>
    <goal_pos>
        <x>18.3239</x>
        <y>2.822</y>
        <vx>0</vx>
        <vy>0</vy>
    </goal_pos>
    <eta>0.0001</eta>
    <sig_obs>29000</sig_obs>
    <sig0>0.30536</sig0>
    <sigT>0.24237</sigT>
    <saving_prefix>/home/zchen927/Documents/VIMP/vimp/save/BRM_20nodes_v1/exp38</saving_prefix>
</Experiment38>
<Experiment39>
    <start_pos>
        <x>10.4108</x>
        <y>16.4603</y>
        <vx>0</vx>
        <vy>0</vy>
    </start_pos>
    <goal_pos>
        <x>13.9305</x>
        <y>9.3877</y>
        <vx>0</vx>
        <vy>0</vy>
    </goal_pos>
    <eta>0.0001</eta>
    <sig_obs>29000</sig_obs>
    <sig0>0.33448</sig0>
    <sigT>0.77462</sigT>
    <saving_prefix>/home/zchen927/Documents/VIMP/vimp/save/BRM_20nodes_v1/exp39</saving_prefix>
</Experiment39>
<Experiment40>
    <start_pos>
        <x>10.4108</x>
        <y>16.4603</y>
        <vx>0</vx>
        <vy>0</vy>
    </start_pos>
    <goal_pos>
        <x>15.5379</x>
        <y>14.7715</y>
        <vx>0</vx>
        <vy>0</vy>
    </goal_pos>
    <eta>0.0001</eta>
    <sig_obs>29000</sig_obs>
    <sig0>0.33448</sig0>
    <sigT>0.77462</sigT>
    <saving_prefix>/home/zchen927/Documents/VIMP/vimp/save/BRM_20nodes_v1/exp40</saving_prefix>
</Experiment40>
<Experiment41>
    <start_pos>
        <x>10.4108</x>
        <y>16.4603</y>
        <vx>0</vx>
        <vy>0</vy>
    </start_pos>
    <goal_pos>
        <x>5.068</x>
        <y>18.2106</y>
        <vx>0</vx>
        <vy>0</vy>
    </goal_pos>
    <eta>0.0001</eta>
    <sig_obs>29000</sig_obs>
    <sig0>0.33448</sig0>
    <sigT>0.21793</sigT>
    <saving_prefix>/home/zchen927/Documents/VIMP/vimp/save/BRM_20nodes_v1/exp41</saving_prefix>
</Experiment41>
<Experiment42>
    <start_pos>
        <x>10.4108</x>
        <y>16.4603</y>
        <vx>0</vx>
        <vy>0</vy>
    </start_pos>
    <goal_pos>
        <x>13</x>
        <y>16</y>
        <vx>0</vx>
        <vy>0</vy>
    </goal_pos>
    <eta>0.0001</eta>
    <sig_obs>29000</sig_obs>
    <sig0>0.33448</sig0>
    <sigT>0.77462</sigT>
    <saving_prefix>/home/zchen927/Documents/VIMP/vimp/save/BRM_20nodes_v1/exp42</saving_prefix>
</Experiment42>
<Experiment43>
    <start_pos>
        <x>15.5379</x>
        <y>14.7715</y>
        <vx>0</vx>
        <vy>0</vy>
    </start_pos>
    <goal_pos>
        <x>13.9305</x>
        <y>9.3877</y>
        <vx>0</vx>
        <vy>0</vy>
    </goal_pos>
    <eta>0.0001</eta>
    <sig_obs>29000</sig_obs>
    <sig0>0.77462</sig0>
    <sigT>0.77462</sigT>
    <saving_prefix>/home/zchen927/Documents/VIMP/vimp/save/BRM_20nodes_v1/exp43</saving_prefix>
</Experiment43>
<Experiment44>
    <start_pos>
        <x>15.5379</x>
        <y>14.7715</y>
        <vx>0</vx>
        <vy>0</vy>
    </start_pos>
    <goal_pos>
        <x>10.4108</x>
        <y>16.4603</y>
        <vx>0</vx>
        <vy>0</vy>
    </goal_pos>
    <eta>0.0001</eta>
    <sig_obs>29000</sig_obs>
    <sig0>0.77462</sig0>
    <sigT>0.33448</sigT>
    <saving_prefix>/home/zchen927/Documents/VIMP/vimp/save/BRM_20nodes_v1/exp44</saving_prefix>
</Experiment44>
<Experiment45>
    <start_pos>
        <x>15.5379</x>
        <y>14.7715</y>
        <vx>0</vx>
        <vy>0</vy>
    </start_pos>
    <goal_pos>
        <x>13</x>
        <y>16</y>
        <vx>0</vx>
        <vy>0</vy>
    </goal_pos>
    <eta>0.0001</eta>
    <sig_obs>29000</sig_obs>
    <sig0>0.77462</sig0>
    <sigT>0.77462</sigT>
    <saving_prefix>/home/zchen927/Documents/VIMP/vimp/save/BRM_20nodes_v1/exp45</saving_prefix>
</Experiment45>
<Experiment46>
    <start_pos>
        <x>5.068</x>
        <y>18.2106</y>
        <vx>0</vx>
        <vy>0</vy>
    </start_pos>
    <goal_pos>
        <x>-0.15114</x>
        <y>13.0219</y>
        <vx>0</vx>
        <vy>0</vy>
    </goal_pos>
    <eta>0.0001</eta>
    <sig_obs>29000</sig_obs>
    <sig0>0.21793</sig0>
    <sigT>0.2352</sigT>
    <saving_prefix>/home/zchen927/Documents/VIMP/vimp/save/BRM_20nodes_v1/exp46</saving_prefix>
</Experiment46>
<Experiment31>
    <start_pos>
        <x>-17.517</x>
        <y>2.3258</y>
        <vx>0</vx>
        <vy>0</vy>
    </start_pos>
    <goal_pos>
        <x>-12.9117</x>
        <y>7.2806</y>
        <vx>0</vx>
        <vy>0</vy>
    </goal_pos>
    <eta>0.0001</eta>
    <sig_obs>29000</sig_obs>
    <sig0>0.35097</sig0>
    <sigT>0.4889</sigT>
    <saving_prefix>/home/zchen927/Documents/VIMP/vimp/save/BRM_20nodes_v1/exp31</saving_prefix>
</Experiment31>
<Experiment48>
    <start_pos>
        <x>5.068</x>
        <y>18.2106</y>
        <vx>0</vx>
        <vy>0</vy>
    </start_pos>
    <goal_pos>
        <x>-3.1484</x>
        <y>18.0263</y>
        <vx>0</vx>
        <vy>0</vy>
    </goal_pos>
    <eta>0.0001</eta>
    <sig_obs>29000</sig_obs>
    <sig0>0.21793</sig0>
    <sigT>0.27141</sigT>
    <saving_prefix>/home/zchen927/Documents/VIMP/vimp/save/BRM_20nodes_v1/exp48</saving_prefix>
</Experiment48>
<Experiment49>
    <start_pos>
        <x>5.068</x>
        <y>18.2106</y>
        <vx>0</vx>
        <vy>0</vy>
    </start_pos>
    <goal_pos>
        <x>13</x>
        <y>16</y>
        <vx>0</vx>
        <vy>0</vy>
    </goal_pos>
    <eta>0.0001</eta>
    <sig_obs>29000</sig_obs>
    <sig0>0.21793</sig0>
    <sigT>0.77462</sigT>
    <saving_prefix>/home/zchen927/Documents/VIMP/vimp/save/BRM_20nodes_v1/exp49</saving_prefix>
</Experiment49>
<Experiment50>
    <start_pos>
        <x>-17.7997</x>
        <y>-4.4425</y>
        <vx>0</vx>
        <vy>0</vy>
    </start_pos>
    <goal_pos>
        <x>-17.517</x>
        <y>2.3258</y>
        <vx>0</vx>
        <vy>0</vy>
    </goal_pos>
    <eta>0.0001</eta>
    <sig_obs>29000</sig_obs>
    <sig0>0.34518</sig0>
    <sigT>0.35097</sigT>
    <saving_prefix>/home/zchen927/Documents/VIMP/vimp/save/BRM_20nodes_v1/exp50</saving_prefix>
</Experiment50>
<Experiment51>
    <start_pos>
        <x>-17.7997</x>
        <y>-4.4425</y>
        <vx>0</vx>
        <vy>0</vy>
    </start_pos>
    <goal_pos>
        <x>-10.1761</x>
        <y>-7.3727</y>
        <vx>0</vx>
        <vy>0</vy>
    </goal_pos>
    <eta>0.0001</eta>
    <sig_obs>29000</sig_obs>
    <sig0>0.34518</sig0>
    <sigT>0.40724</sigT>
    <saving_prefix>/home/zchen927/Documents/VIMP/vimp/save/BRM_20nodes_v1/exp51</saving_prefix>
</Experiment51>
<Experiment52>
    <start_pos>
        <x>0.90345</x>
        <y>-6.471</y>
        <vx>0</vx>
        <vy>0</vy>
    </start_pos>
    <goal_pos>
        <x>6.0827</x>
        <y>-3.8465</y>
        <vx>0</vx>
        <vy>0</vy>
    </goal_pos>
    <eta>0.0001</eta>
    <sig_obs>29000</sig_obs>
    <sig0>0.77462</sig0>
    <sigT>0.1194</sigT>
    <saving_prefix>/home/zchen927/Documents/VIMP/vimp/save/BRM_20nodes_v1/exp52</saving_prefix>
</Experiment52>
<Experiment53>
    <start_pos>
        <x>0.90345</x>
        <y>-6.471</y>
        <vx>0</vx>
        <vy>0</vy>
    </start_pos>
    <goal_pos>
        <x>-6.396</x>
        <y>-3.5565</y>
        <vx>0</vx>
        <vy>0</vy>
    </goal_pos>
    <eta>0.0001</eta>
    <sig_obs>29000</sig_obs>
    <sig0>0.77462</sig0>
    <sigT>0.34647</sigT>
    <saving_prefix>/home/zchen927/Documents/VIMP/vimp/save/BRM_20nodes_v1/exp53</saving_prefix>
</Experiment53>
<Experiment54>
    <start_pos>
        <x>-3.1484</x>
        <y>18.0263</y>
        <vx>0</vx>
        <vy>0</vy>
    </start_pos>
    <goal_pos>
        <x>-0.15114</x>
        <y>13.0219</y>
        <vx>0</vx>
        <vy>0</vy>
    </goal_pos>
    <eta>0.0001</eta>
    <sig_obs>29000</sig_obs>
    <sig0>0.27141</sig0>
    <sigT>0.2352</sigT>
    <saving_prefix>/home/zchen927/Documents/VIMP/vimp/save/BRM_20nodes_v1/exp54</saving_prefix>
</Experiment54>
<Experiment55>
    <start_pos>
        <x>-3.1484</x>
        <y>18.0263</y>
        <vx>0</vx>
        <vy>0</vy>
    </start_pos>
    <goal_pos>
        <x>-8.2745</x>
        <y>18.6513</y>
        <vx>0</vx>
        <vy>0</vy>
    </goal_pos>
    <eta>0.0001</eta>
    <sig_obs>29000</sig_obs>
    <sig0>0.27141</sig0>
    <sigT>0.11385</sigT>
    <saving_prefix>/home/zchen927/Documents/VIMP/vimp/save/BRM_20nodes_v1/exp55</saving_prefix>
</Experiment55>
<Experiment56>
    <start_pos>
        <x>-3.1484</x>
        <y>18.0263</y>
        <vx>0</vx>
        <vy>0</vy>
    </start_pos>
    <goal_pos>
        <x>5.068</x>
        <y>18.2106</y>
        <vx>0</vx>
        <vy>0</vy>
    </goal_pos>
    <eta>0.0001</eta>
    <sig_obs>29000</sig_obs>
    <sig0>0.27141</sig0>
    <sigT>0.21793</sigT>
    <saving_prefix>/home/zchen927/Documents/VIMP/vimp/save/BRM_20nodes_v1/exp56</saving_prefix>
</Experiment56>
<Experiment57>
    <start_pos>
        <x>-10.1761</x>
        <y>-7.3727</y>
        <vx>0</vx>
        <vy>0</vy>
    </start_pos>
    <goal_pos>
        <x>-6.396</x>
        <y>-3.5565</y>
        <vx>0</vx>
        <vy>0</vy>
    </goal_pos>
    <eta>0.0001</eta>
    <sig_obs>29000</sig_obs>
    <sig0>0.40724</sig0>
    <sigT>0.34647</sigT>
    <saving_prefix>/home/zchen927/Documents/VIMP/vimp/save/BRM_20nodes_v1/exp57</saving_prefix>
</Experiment57>
<Experiment58>
    <start_pos>
        <x>-10.1761</x>
        <y>-7.3727</y>
        <vx>0</vx>
        <vy>0</vy>
    </start_pos>
    <goal_pos>
        <x>-17.7997</x>
        <y>-4.4425</y>
        <vx>0</vx>
        <vy>0</vy>
    </goal_pos>
    <eta>0.0001</eta>
    <sig_obs>29000</sig_obs>
    <sig0>0.40724</sig0>
    <sigT>0.34518</sigT>
    <saving_prefix>/home/zchen927/Documents/VIMP/vimp/save/BRM_20nodes_v1/exp58</saving_prefix>
</Experiment58>
<Experiment59>
    <start_pos>
        <x>13</x>
        <y>16</y>
        <vx>0</vx>
        <vy>0</vy>
    </start_pos>
    <goal_pos>
        <x>13.9305</x>
        <y>9.3877</y>
        <vx>0</vx>
        <vy>0</vy>
    </goal_pos>
    <eta>0.0001</eta>
    <sig_obs>29000</sig_obs>
    <sig0>0.77462</sig0>
    <sigT>0.77462</sigT>
    <saving_prefix>/home/zchen927/Documents/VIMP/vimp/save/BRM_20nodes_v1/exp59</saving_prefix>
</Experiment59>
<Experiment60>
    <start_pos>
        <x>13</x>
        <y>16</y>
        <vx>0</vx>
        <vy>0</vy>
    </start_pos>
    <goal_pos>
        <x>10.4108</x>
        <y>16.4603</y>
        <vx>0</vx>
        <vy>0</vy>
    </goal_pos>
    <eta>0.0001</eta>
    <sig_obs>29000</sig_obs>
    <sig0>0.77462</sig0>
    <sigT>0.33448</sigT>
    <saving_prefix>/home/zchen927/Documents/VIMP/vimp/save/BRM_20nodes_v1/exp60</saving_prefix>
</Experiment60>
<Experiment61>
    <start_pos>
        <x>13</x>
        <y>16</y>
        <vx>0</vx>
        <vy>0</vy>
    </start_pos>
    <goal_pos>
        <x>15.5379</x>
        <y>14.7715</y>
        <vx>0</vx>
        <vy>0</vy>
    </goal_pos>
    <eta>0.0001</eta>
    <sig_obs>29000</sig_obs>
    <sig0>0.77462</sig0>
    <sigT>0.77462</sigT>
    <saving_prefix>/home/zchen927/Documents/VIMP/vimp/save/BRM_20nodes_v1/exp61</saving_prefix>
</Experiment61>
<Experiment62>
    <start_pos>
        <x>13</x>
        <y>16</y>
        <vx>0</vx>
        <vy>0</vy>
    </start_pos>
    <goal_pos>
        <x>5.068</x>
        <y>18.2106</y>
        <vx>0</vx>
        <vy>0</vy>
    </goal_pos>
    <eta>0.0001</eta>
    <sig_obs>29000</sig_obs>
    <sig0>0.77462</sig0>
    <sigT>0.21793</sigT>
    <saving_prefix>/home/zchen927/Documents/VIMP/vimp/save/BRM_20nodes_v1/exp62</saving_prefix>
</Experiment62>
<Experiment16>
    <start_pos>
        <x>8.4615</x>
        <y>3.6868</y>
        <vx>0</vx>
        <vy>0</vy>
    </start_pos>
    <goal_pos>
        <x>13.9305</x>
        <y>9.3877</y>
        <vx>0</vx>
        <vy>0</vy>
    </goal_pos>
    <eta>0.0001</eta>
    <sig_obs>29000</sig_obs>
    <sig0>0.093043</sig0>
    <sigT>0.77462</sigT>
    <saving_prefix>/home/zchen927/Documents/VIMP/vimp/save/BRM_20nodes_v1/exp16</saving_prefix>
</Experiment16>
<Experiment1>
    <start_pos>
        <x>-16</x>
        <y>17</y>
        <vx>0</vx>
        <vy>0</vy>
    </start_pos>
    <goal_pos>
        <x>-17.7769</x>
        <y>9.3024</y>
        <vx>0</vx>
        <vy>0</vy>
    </goal_pos>
    <eta>0.0001</eta>
    <sig_obs>29000</sig_obs>
    <sig0>0.67634</sig0>
    <sigT>0.3531</sigT>
    <saving_prefix>/home/zchen927/Documents/VIMP/vimp/save/BRM_20nodes_v1/exp1</saving_prefix>
</Experiment1>
<Experiment2>
    <start_pos>
        <x>-16</x>
        <y>17</y>
        <vx>0</vx>
        <vy>0</vy>
    </start_pos>
    <goal_pos>
        <x>-8.2745</x>
        <y>18.6513</y>
        <vx>0</vx>
        <vy>0</vy>
    </goal_pos>
    <eta>0.0001</eta>
    <sig_obs>29000</sig_obs>
    <sig0>0.67634</sig0>
    <sigT>0.11385</sigT>
    <saving_prefix>/home/zchen927/Documents/VIMP/vimp/save/BRM_20nodes_v1/exp2</saving_prefix>
</Experiment2>
<Experiment3>
    <start_pos>
        <x>-17.7769</x>
        <y>9.3024</y>
        <vx>0</vx>
        <vy>0</vy>
    </start_pos>
    <goal_pos>
        <x>-16</x>
        <y>17</y>
        <vx>0</vx>
        <vy>0</vy>
    </goal_pos>
    <eta>0.0001</eta>
    <sig_obs>29000</sig_obs>
    <sig0>0.3531</sig0>
    <sigT>0.67634</sigT>
    <saving_prefix>/home/zchen927/Documents/VIMP/vimp/save/BRM_20nodes_v1/exp3</saving_prefix>
</Experiment3>
<Experiment4>
    <start_pos>
        <x>-17.7769</x>
        <y>9.3024</y>
        <vx>0</vx>
        <vy>0</vy>
    </start_pos>
    <goal_pos>
        <x>-12.9117</x>
        <y>7.2806</y>
        <vx>0</vx>
        <vy>0</vy>
    </goal_pos>
    <eta>0.0001</eta>
    <sig_obs>29000</sig_obs>
    <sig0>0.3531</sig0>
    <sigT>0.4889</sigT>
    <saving_prefix>/home/zchen927/Documents/VIMP/vimp/save/BRM_20nodes_v1/exp4</saving_prefix>
</Experiment4>
<Experiment5>
    <start_pos>
        <x>-17.7769</x>
        <y>9.3024</y>
        <vx>0</vx>
        <vy>0</vy>
    </start_pos>
    <goal_pos>
        <x>-17.517</x>
        <y>2.3258</y>
        <vx>0</vx>
        <vy>0</vy>
    </goal_pos>
    <eta>0.0001</eta>
    <sig_obs>29000</sig_obs>
    <sig0>0.3531</sig0>
    <sigT>0.35097</sigT>
    <saving_prefix>/home/zchen927/Documents/VIMP/vimp/save/BRM_20nodes_v1/exp5</saving_prefix>
</Experiment5>
<Experiment6>
    <start_pos>
        <x>-12.9117</x>
        <y>7.2806</y>
        <vx>0</vx>
        <vy>0</vy>
    </start_pos>
    <goal_pos>
        <x>-17.7769</x>
        <y>9.3024</y>
        <vx>0</vx>
        <vy>0</vy>
    </goal_pos>
    <eta>0.0001</eta>
    <sig_obs>29000</sig_obs>
    <sig0>0.4889</sig0>
    <sigT>0.3531</sigT>
    <saving_prefix>/home/zchen927/Documents/VIMP/vimp/save/BRM_20nodes_v1/exp6</saving_prefix>
</Experiment6>
<Experiment7>
    <start_pos>
        <x>-12.9117</x>
        <y>7.2806</y>
        <vx>0</vx>
        <vy>0</vy>
    </start_pos>
    <goal_pos>
        <x>-5.5944</x>
        <y>4.3028</y>
        <vx>0</vx>
        <vy>0</vy>
    </goal_pos>
    <eta>0.0001</eta>
    <sig_obs>29000</sig_obs>
    <sig0>0.4889</sig0>
    <sigT>0.67903</sigT>
    <saving_prefix>/home/zchen927/Documents/VIMP/vimp/save/BRM_20nodes_v1/exp7</saving_prefix>
</Experiment7>
<Experiment8>
    <start_pos>
        <x>-12.9117</x>
        <y>7.2806</y>
        <vx>0</vx>
        <vy>0</vy>
    </start_pos>
    <goal_pos>
        <x>-17.517</x>
        <y>2.3258</y>
        <vx>0</vx>
        <vy>0</vy>
    </goal_pos>
    <eta>0.0001</eta>
    <sig_obs>29000</sig_obs>
    <sig0>0.4889</sig0>
    <sigT>0.35097</sigT>
    <saving_prefix>/home/zchen927/Documents/VIMP/vimp/save/BRM_20nodes_v1/exp8</saving_prefix>
</Experiment8>
<Experiment9>
    <start_pos>
        <x>-5.5944</x>
        <y>4.3028</y>
        <vx>0</vx>
        <vy>0</vy>
    </start_pos>
    <goal_pos>
        <x>-12.9117</x>
        <y>7.2806</y>
        <vx>0</vx>
        <vy>0</vy>
    </goal_pos>
    <eta>0.0001</eta>
    <sig_obs>29000</sig_obs>
    <sig0>0.67903</sig0>
    <sigT>0.4889</sigT>
    <saving_prefix>/home/zchen927/Documents/VIMP/vimp/save/BRM_20nodes_v1/exp9</saving_prefix>
</Experiment9>
<Experiment10>
    <start_pos>
        <x>-5.5944</x>
        <y>4.3028</y>
        <vx>0</vx>
        <vy>0</vy>
    </start_pos>
    <goal_pos>
        <x>1.0018</x>
        <y>6.2873</y>
        <vx>0</vx>
        <vy>0</vy>
    </goal_pos>
    <eta>0.0001</eta>
    <sig_obs>29000</sig_obs>
    <sig0>0.67903</sig0>
    <sigT>0.25307</sigT>
    <saving_prefix>/home/zchen927/Documents/VIMP/vimp/save/BRM_20nodes_v1/exp10</saving_prefix>
</Experiment10>
<Experiment11>
    <start_pos>
        <x>-5.5944</x>
        <y>4.3028</y>
        <vx>0</vx>
        <vy>0</vy>
    </start_pos>
    <goal_pos>
        <x>-6.396</x>
        <y>-3.5565</y>
        <vx>0</vx>
        <vy>0</vy>
    </goal_pos>
    <eta>0.0001</eta>
    <sig_obs>29000</sig_obs>
    <sig0>0.67903</sig0>
    <sigT>0.34647</sigT>
    <saving_prefix>/home/zchen927/Documents/VIMP/vimp/save/BRM_20nodes_v1/exp11</saving_prefix>
</Experiment11>
<Experiment12>
    <start_pos>
        <x>1.0018</x>
        <y>6.2873</y>
        <vx>0</vx>
        <vy>0</vy>
    </start_pos>
    <goal_pos>
        <x>-5.5944</x>
        <y>4.3028</y>
        <vx>0</vx>
        <vy>0</vy>
    </goal_pos>
    <eta>0.0001</eta>
    <sig_obs>29000</sig_obs>
    <sig0>0.25307</sig0>
    <sigT>0.67903</sigT>
    <saving_prefix>/home/zchen927/Documents/VIMP/vimp/save/BRM_20nodes_v1/exp12</saving_prefix>
</Experiment12>
<Experiment13>
    <start_pos>
        <x>1.0018</x>
        <y>6.2873</y>
        <vx>0</vx>
        <vy>0</vy>
    </start_pos>
    <goal_pos>
        <x>8.4615</x>
        <y>3.6868</y>
        <vx>0</vx>
        <vy>0</vy>
    </goal_pos>
    <eta>0.0001</eta>
    <sig_obs>29000</sig_obs>
    <sig0>0.25307</sig0>
    <sigT>0.093043</sigT>
    <saving_prefix>/home/zchen927/Documents/VIMP/vimp/save/BRM_20nodes_v1/exp13</saving_prefix>
</Experiment13>
<Experiment14>
    <start_pos>
        <x>1.0018</x>
        <y>6.2873</y>
        <vx>0</vx>
        <vy>0</vy>
    </start_pos>
    <goal_pos>
        <x>-0.15114</x>
        <y>13.0219</y>
        <vx>0</vx>
        <vy>0</vy>
    </goal_pos>
    <eta>0.0001</eta>
    <sig_obs>29000</sig_obs>
    <sig0>0.25307</sig0>
    <sigT>0.2352</sigT>
    <saving_prefix>/home/zchen927/Documents/VIMP/vimp/save/BRM_20nodes_v1/exp14</saving_prefix>
</Experiment14>
<Experiment15>
    <start_pos>
        <x>8.4615</x>
        <y>3.6868</y>
        <vx>0</vx>
        <vy>0</vy>
    </start_pos>
    <goal_pos>
        <x>1.0018</x>
        <y>6.2873</y>
        <vx>0</vx>
        <vy>0</vy>
    </goal_pos>
    <eta>0.0001</eta>
    <sig_obs>29000</sig_obs>
    <sig0>0.093043</sig0>
    <sigT>0.25307</sigT>
    <saving_prefix>/home/zchen927/Documents/VIMP/vimp/save/BRM_20nodes_v1/exp15</saving_prefix>
</Experiment15>
<Commons>
    <eps>0.01</eps>
    <eps_sdf>0.6</eps_sdf>
    <radius>1.5</radius>
    <total_time>1.5</total_time>
    <nt>50</nt>
    <sig0>0.01</sig0>
    <sigT>0.05</sigT>
    <eta>0.0001</eta>
    <stop_err>0.001</stop_err>
    <max_iter>50</max_iter>
    <map_name>2dpr_map2</map_name>
    <sig_obs>20000</sig_obs>
    <backtracking_ratio>0.7</backtracking_ratio>
    <max_n_backtracking>3</max_n_backtracking>
</Commons>
<Experiment17>
    <start_pos>
        <x>8.4615</x>
        <y>3.6868</y>
        <vx>0</vx>
        <vy>0</vy>
    </start_pos>
    <goal_pos>
        <x>6.0827</x>
        <y>-3.8465</y>
        <vx>0</vx>
        <vy>0</vy>
    </goal_pos>
    <eta>0.0001</eta>
    <sig_obs>29000</sig_obs>
    <sig0>0.093043</sig0>
    <sigT>0.1194</sigT>
    <saving_prefix>/home/zchen927/Documents/VIMP/vimp/save/BRM_20nodes_v1/exp17</saving_prefix>
</Experiment17>
<Experiment18>
    <start_pos>
        <x>13.9305</x>
        <y>9.3877</y>
        <vx>0</vx>
        <vy>0</vy>
    </start_pos>
    <goal_pos>
        <x>8.4615</x>
        <y>3.6868</y>
        <vx>0</vx>
        <vy>0</vy>
    </goal_pos>
    <eta>0.0001</eta>
    <sig_obs>29000</sig_obs>
    <sig0>0.77462</sig0>
    <sigT>0.093043</sigT>
    <saving_prefix>/home/zchen927/Documents/VIMP/vimp/save/BRM_20nodes_v1/exp18</saving_prefix>
</Experiment18>
<Experiment19>
    <start_pos>
        <x>13.9305</x>
        <y>9.3877</y>
        <vx>0</vx>
        <vy>0</vy>
    </start_pos>
    <goal_pos>
        <x>18.3239</x>
        <y>2.822</y>
        <vx>0</vx>
        <vy>0</vy>
    </goal_pos>
    <eta>0.0001</eta>
    <sig_obs>29000</sig_obs>
    <sig0>0.77462</sig0>
    <sigT>0.24237</sigT>
    <saving_prefix>/home/zchen927/Documents/VIMP/vimp/save/BRM_20nodes_v1/exp19</saving_prefix>
</Experiment19>
<Experiment20>
    <start_pos>
        <x>13.9305</x>
        <y>9.3877</y>
        <vx>0</vx>
        <vy>0</vy>
    </start_pos>
    <goal_pos>
        <x>10.4108</x>
        <y>16.4603</y>
        <vx>0</vx>
        <vy>0</vy>
    </goal_pos>
    <eta>0.0001</eta>
    <sig_obs>29000</sig_obs>
    <sig0>0.77462</sig0>
    <sigT>0.33448</sigT>
    <saving_prefix>/home/zchen927/Documents/VIMP/vimp/save/BRM_20nodes_v1/exp20</saving_prefix>
</Experiment20>
<Experiment21>
    <start_pos>
        <x>13.9305</x>
        <y>9.3877</y>
        <vx>0</vx>
        <vy>0</vy>
    </start_pos>
    <goal_pos>
        <x>15.5379</x>
        <y>14.7715</y>
        <vx>0</vx>
        <vy>0</vy>
    </goal_pos>
    <eta>0.0001</eta>
    <sig_obs>29000</sig_obs>
    <sig0>0.77462</sig0>
    <sigT>0.77462</sigT>
    <saving_prefix>/home/zchen927/Documents/VIMP/vimp/save/BRM_20nodes_v1/exp21</saving_prefix>
</Experiment21>
<Experiment22>
    <start_pos>
        <x>13.9305</x>
        <y>9.3877</y>
        <vx>0</vx>
        <vy>0</vy>
    </start_pos>
    <goal_pos>
        <x>13</x>
        <y>16</y>
        <vx>0</vx>
        <vy>0</vy>
    </goal_pos>
    <eta>0.0001</eta>
    <sig_obs>29000</sig_obs>
    <sig0>0.77462</sig0>
    <sigT>0.77462</sigT>
    <saving_prefix>/home/zchen927/Documents/VIMP/vimp/save/BRM_20nodes_v1/exp22</saving_prefix>
</Experiment22>
<Experiment23>
    <start_pos>
        <x>18.3239</x>
        <y>2.822</y>
        <vx>0</vx>
        <vy>0</vy>
    </start_pos>
    <goal_pos>
        <x>13.9305</x>
        <y>9.3877</y>
        <vx>0</vx>
        <vy>0</vy>
    </goal_pos>
    <eta>0.0001</eta>
    <sig_obs>29000</sig_obs>
    <sig0>0.24237</sig0>
    <sigT>0.77462</sigT>
    <saving_prefix>/home/zchen927/Documents/VIMP/vimp/save/BRM_20nodes_v1/exp23</saving_prefix>
</Experiment23>
<Experiment24>
    <start_pos>
        <x>18.3239</x>
        <y>2.822</y>
        <vx>0</vx>
        <vy>0</vy>
    </start_pos>
    <goal_pos>
        <x>18.1186</x>
        <y>-5.0753</y>
        <vx>0</vx>
        <vy>0</vy>
    </goal_pos>
    <eta>0.0001</eta>
    <sig_obs>29000</sig_obs>
    <sig0>0.24237</sig0>
    <sigT>0.30536</sigT>
    <saving_prefix>/home/zchen927/Documents/VIMP/vimp/save/BRM_20nodes_v1/exp24</saving_prefix>
</Experiment24>
<Experiment25>
    <start_pos>
        <x>-0.15114</x>
        <y>13.0219</y>
        <vx>0</vx>
        <vy>0</vy>
    </start_pos>
    <goal_pos>
        <x>1.0018</x>
        <y>6.2873</y>
        <vx>0</vx>
        <vy>0</vy>
    </goal_pos>
    <eta>0.0001</eta>
    <sig_obs>29000</sig_obs>
    <sig0>0.2352</sig0>
    <sigT>0.25307</sigT>
    <saving_prefix>/home/zchen927/Documents/VIMP/vimp/save/BRM_20nodes_v1/exp25</saving_prefix>
</Experiment25>
<Experiment26>
    <start_pos>
        <x>-0.15114</x>
        <y>13.0219</y>
        <vx>0</vx>
        <vy>0</vy>
    </start_pos>
    <goal_pos>
        <x>5.068</x>
        <y>18.2106</y>
        <vx>0</vx>
        <vy>0</vy>
    </goal_pos>
    <eta>0.0001</eta>
    <sig_obs>29000</sig_obs>
    <sig0>0.2352</sig0>
    <sigT>0.21793</sigT>
    <saving_prefix>/home/zchen927/Documents/VIMP/vimp/save/BRM_20nodes_v1/exp26</saving_prefix>
</Experiment26>
<Experiment27>
    <start_pos>
        <x>-0.15114</x>
        <y>13.0219</y>
        <vx>0</vx>
        <vy>0</vy>
    </start_pos>
    <goal_pos>
        <x>-3.1484</x>
        <y>18.0263</y>
        <vx>0</vx>
        <vy>0</vy>
    </goal_pos>
    <eta>0.0001</eta>
    <sig_obs>29000</sig_obs>
    <sig0>0.2352</sig0>
    <sigT>0.27141</sigT>
    <saving_prefix>/home/zchen927/Documents/VIMP/vimp/save/BRM_20nodes_v1/exp27</saving_prefix>
</Experiment27>
<Experiment28>
    <start_pos>
        <x>6.0827</x>
        <y>-3.8465</y>
        <vx>0</vx>
        <vy>0</vy>
    </start_pos>
    <goal_pos>
        <x>8.4615</x>
        <y>3.6868</y>
        <vx>0</vx>
        <vy>0</vy>
    </goal_pos>
    <eta>0.0001</eta>
    <sig_obs>29000</sig_obs>
    <sig0>0.1194</sig0>
    <sigT>0.093043</sigT>
    <saving_prefix>/home/zchen927/Documents/VIMP/vimp/save/BRM_20nodes_v1/exp28</saving_prefix>
</Experiment28>
<Experiment29>
    <start_pos>
        <x>6.0827</x>
        <y>-3.8465</y>
        <vx>0</vx>
        <vy>0</vy>
    </start_pos>
    <goal_pos>
        <x>0.90345</x>
        <y>-6.471</y>
        <vx>0</vx>
        <vy>0</vy>
    </goal_pos>
    <eta>0.0001</eta>
    <sig_obs>29000</sig_obs>
    <sig0>0.1194</sig0>
    <sigT>0.77462</sigT>
    <saving_prefix>/home/zchen927/Documents/VIMP/vimp/save/BRM_20nodes_v1/exp29</saving_prefix>
</Experiment29>
<Experiment30>
    <start_pos>
        <x>-17.517</x>
        <y>2.3258</y>
        <vx>0</vx>
        <vy>0</vy>
    </start_pos>
    <goal_pos>
        <x>-17.7769</x>
        <y>9.3024</y>
        <vx>0</vx>
        <vy>0</vy>
    </goal_pos>
    <eta>0.0001</eta>
    <sig_obs>29000</sig_obs>
    <sig0>0.35097</sig0>
    <sigT>0.3531</sigT>
    <saving_prefix>/home/zchen927/Documents/VIMP/vimp/save/BRM_20nodes_v1/exp30</saving_prefix>
</Experiment30>

